ispec/__init__.py
ispec/_modidx.py
ispec/agg.py
ispec/ann.py
ispec/dec.py
ispec/dun.py
ispec/enums.py
ispec/kws.py
ispec/preps.py
ispec/rnk.py
ispec/sattr.py
ispec/set.py
ispec/sig.py
ispec/src.py
ispec/tests.py
ispec/types.py
ispec/utils.py
ispec/val.py
ispec-0.0.18.dist-info/LICENSE
ispec-0.0.18.dist-info/METADATA
ispec-0.0.18.dist-info/WHEEL
ispec-0.0.18.dist-info/entry_points.txt
ispec-0.0.18.dist-info/top_level.txt
ispec-0.0.18.dist-info/RECORD
