Metadata-Version: 2.1
Name: ispec
Version: 0.0.18
Summary: ispec
Home-page: https://github.com/dsm-72/ispec
Author: dsm-72
Author-email: sumner.magruder@yale.edu
License: Apache Software License 2.0
Keywords: nbdev jupyter notebook python inspect ispec utils args kwo kwargs kwonly
Classifier: Development Status :: 4 - Beta
Classifier: Intended Audience :: Developers
Classifier: Natural Language :: English
Classifier: Programming Language :: Python :: 3.11
Classifier: License :: OSI Approved :: Apache Software License
Requires-Python: >=3.11
License-File: LICENSE
Requires-Dist: nchr
Requires-Dist: nlit
Requires-Dist: quac
Requires-Dist: chck
Requires-Dist: ropts
Provides-Extra: dev
